{
	"id": "07d54407-c639-4abd-adfd-51f38293101e",
	"name": "Spotify",
	"values": [
		{
			"key": "baseUrl",
			"value": "https://api.spotify.com/v1",
			"enabled": true
		},
		{
			"key": "userId",
			"value": "",
			"enabled": true
		},
		{
			"key": "token",
			"value": "xxxx",
			"enabled": true
		},
		{
			"key": "playlistId",
			"value": "",
			"enabled": true
		},
		{
			"key": "version",
			"value": "v1",
			"enabled": true
		},
		{
			"key": "trackUri1",
			"value": "",
			"enabled": true
		},
		{
			"key": "trackUri2",
			"value": "",
			"enabled": true
		},
		{
			"key": "srId",
			"value": "",
			"enabled": true
		}
	],
	"_postman_variable_scope": "environment",
	"_postman_exported_at": "2021-08-03T08:07:45.298Z",
	"_postman_exported_using": "Postman/8.9.1"
}